octopus_agent/__init__.py
octopus_agent/agent_builder.py
octopus_agent/agent_llm.py
octopus_agent/agent_server.py
octopus_agent/agent_setup.py
octopus_agent/base_agent.py
octopus_agent/base_stream_client.py
octopus_agent/codellama_agent.py
octopus_agent/codellama_client.py
octopus_agent/grammar.bnf
octopus_agent/mock_agent.py
octopus_agent/mock_tools.py
octopus_agent/openai_agent.py
octopus_agent/prompt.py
octopus_agent/tokenizer.py
octopus_agent-0.4.18.dist-info/METADATA
octopus_agent-0.4.18.dist-info/WHEEL
octopus_agent-0.4.18.dist-info/entry_points.txt
octopus_agent-0.4.18.dist-info/top_level.txt
octopus_agent-0.4.18.dist-info/RECORD
