Metadata-Version: 2.1
Name: octopus-agent
Version: 0.4.18
Summary: Open source code interpreter agent
Home-page: https://github.com/dbpunk-labs/octopus
Author: imotai
Author-email: wangtaize@dbpunk.com
Requires-Dist: octopus-proto
Requires-Dist: octopus-kernel
Requires-Dist: octopus-sdk
Requires-Dist: grpcio-tools >=1.57.0
Requires-Dist: grpc-google-iam-v1 >=0.12.6
Requires-Dist: aiofiles
Requires-Dist: orm[sqlite]
Requires-Dist: python-dotenv
Requires-Dist: openai
Requires-Dist: aiohttp >=3.8.5
Requires-Dist: pydantic
